{
  "kind": "collectionType",
  "collectionName": "prices",
  "info": {
    "name": "price",
    "description": ""
  },
  "options": {
    "increments": true,
    "timestamps": true,
    "draftAndPublish": true
  },
  "attributes": {
    "title": {
      "type": "string"
    },
    "price": {
      "type": "integer"
    },
    "users": {
      "type": "string"
    },
    "admins": {
      "type": "string"
    },
    "modules": {
      "type": "string"
    },
    "moduleItem": {
      "type": "component",
      "repeatable": true,
      "component": "bloom.module-item"
    },
    "popular": {
      "type": "boolean",
      "default": false
    },
    "subtitle": {
      "type": "string"
    }
  }
}
